{
  "D:\\otros\\Softekk_Prueba_Tecnica\\starwars-api": {
    "versionSfCore": null,
    "versionFramework": "4.4.6",
    "isWithinCompose": false,
    "isCompose": false,
    "composeOrgName": null,
    "composeResolverProviders": {
      "default-aws-credential-resolver": "<REDACTED>",
      "env": {
        "instance": {
          "credentials": "<REDACTED>",
          "serviceConfigFile": {
            "service": "starwars-api",
            "plugins": [
              "serverless-jetpack",
              "serverless-offline"
            ],
            "useDotenv": true,
            "frameworkVersion": "4",
            "provider": {
              "name": "aws",
              "runtime": "nodejs18.x",
              "environment": {
                "SWAPI_URL": "https://swapi.py4e.com/api",
                "DATABASE_URL": "mysql://admin:zNvem55R6rGVHLZ@evaluacion-softtek.c9qmai44axdb.us-east-1.rds.amazonaws.com:3306/starwars?schema=public"
              },
              "vpc": {
                "subnetIds": [
                  "subnet-0bf79a58960460c7e",
                  "subnet-055feaddca913028c",
                  "subnet-0e17a2d20a160af93",
                  "subnet-0dddebcd6bb360117",
                  "subnet-0ffdbdde1b7f4cbec",
                  "subnet-0b9b7771bef7496d9"
                ],
                "securityGroupIds": [
                  "sg-0565b976b97262683"
                ]
              },
              "apiGateway": {
                "name": "starwars-api-gateway",
                "version": "v2",
                "cors": {
                  "origins": [
                    "*"
                  ],
                  "methods": [
                    "GET",
                    "POST",
                    "PUT",
                    "DELETE",
                    "HEAD"
                  ],
                  "headers": [
                    "Content-Type",
                    "Authorization"
                  ],
                  "allowCredentials": "<REDACTED>"
                }
              },
              "stage": "dev",
              "region": "us-east-1",
              "versionFunctions": true,
              "compiledCloudFormationTemplate": {
                "AWSTemplateFormatVersion": "2010-09-09",
                "Description": "The AWS CloudFormation template for this Serverless application",
                "Resources": {
                  "MainLogGroup": {
                    "Type": "AWS::Logs::LogGroup",
                    "Properties": {
                      "LogGroupName": "/aws/lambda/starwars-api-dev-main"
                    }
                  },
                  "IamRoleLambdaExecution": {
                    "Type": "AWS::IAM::Role",
                    "Properties": {
                      "AssumeRolePolicyDocument": {
                        "Version": "2012-10-17",
                        "Statement": [
                          {
                            "Effect": "Allow",
                            "Principal": {
                              "Service": [
                                "lambda.amazonaws.com"
                              ]
                            },
                            "Action": [
                              "sts:AssumeRole"
                            ]
                          }
                        ]
                      },
                      "Policies": [
                        {
                          "PolicyName": {
                            "Fn::Join": [
                              "-",
                              [
                                "starwars-api",
                                "dev",
                                "lambda"
                              ]
                            ]
                          },
                          "PolicyDocument": {
                            "Version": "2012-10-17",
                            "Statement": [
                              {
                                "Effect": "Allow",
                                "Action": [
                                  "logs:CreateLogStream",
                                  "logs:CreateLogGroup",
                                  "logs:TagResource"
                                ],
                                "Resource": [
                                  {
                                    "Fn::Sub": "arn:${AWS::Partition}:logs:${AWS::Region}:${AWS::AccountId}:log-group:/aws/lambda/starwars-api-dev*:*"
                                  }
                                ]
                              },
                              {
                                "Effect": "Allow",
                                "Action": [
                                  "logs:PutLogEvents"
                                ],
                                "Resource": [
                                  {
                                    "Fn::Sub": "arn:${AWS::Partition}:logs:${AWS::Region}:${AWS::AccountId}:log-group:/aws/lambda/starwars-api-dev*:*:*"
                                  }
                                ]
                              }
                            ]
                          }
                        }
                      ],
                      "Path": "/",
                      "RoleName": {
                        "Fn::Join": [
                          "-",
                          [
                            "starwars-api",
                            "dev",
                            {
                              "Ref": "AWS::Region"
                            },
                            "lambdaRole"
                          ]
                        ]
                      },
                      "ManagedPolicyArns": [
                        {
                          "Fn::Join": [
                            "",
                            [
                              "arn:",
                              {
                                "Ref": "AWS::Partition"
                              },
                              ":iam::aws:policy/service-role/AWSLambdaVPCAccessExecutionRole"
                            ]
                          ]
                        }
                      ]
                    }
                  },
                  "MainLambdaFunction": {
                    "Type": "AWS::Lambda::Function",
                    "Properties": {
                      "Code": {
                        "S3Bucket": "serverless-framework-deployments-us-east-1-4b88c842-fa16",
                        "S3Key": "serverless/starwars-api/dev/1729389127459-2024-10-20T01:52:07.459Z/starwars-api.zip"
                      },
                      "Handler": "dist/serverless.handler",
                      "Runtime": "nodejs18.x",
                      "FunctionName": "starwars-api-dev-main",
                      "MemorySize": 1024,
                      "Timeout": 6,
                      "Environment": {
                        "Variables": {
                          "SWAPI_URL": "https://swapi.py4e.com/api",
                          "DATABASE_URL": "mysql://admin:zNvem55R6rGVHLZ@evaluacion-softtek.c9qmai44axdb.us-east-1.rds.amazonaws.com:3306/starwars?schema=public"
                        }
                      },
                      "Role": {
                        "Fn::GetAtt": [
                          "IamRoleLambdaExecution",
                          "Arn"
                        ]
                      },
                      "VpcConfig": {
                        "SecurityGroupIds": [
                          "sg-0565b976b97262683"
                        ],
                        "SubnetIds": [
                          "subnet-0bf79a58960460c7e",
                          "subnet-055feaddca913028c",
                          "subnet-0e17a2d20a160af93",
                          "subnet-0dddebcd6bb360117",
                          "subnet-0ffdbdde1b7f4cbec",
                          "subnet-0b9b7771bef7496d9"
                        ]
                      }
                    },
                    "DependsOn": [
                      "MainLogGroup"
                    ]
                  },
                  "MainLambdaVersion5NNZ5akh00CMyrCCTqWh3fsBIltcwBfyVgr2QKffk": {
                    "Type": "AWS::Lambda::Version",
                    "DeletionPolicy": "Retain",
                    "Properties": {
                      "FunctionName": {
                        "Ref": "MainLambdaFunction"
                      },
                      "CodeSha256": "qRbSlCBV8HAakXSem4jfLrWCoaN1gpgOkE8DB3/Du44="
                    }
                  },
                  "ApiGatewayRestApi": {
                    "Type": "AWS::ApiGateway::RestApi",
                    "Properties": {
                      "Name": "dev-starwars-api",
                      "EndpointConfiguration": {
                        "Types": [
                          "EDGE"
                        ]
                      },
                      "Policy": ""
                    }
                  },
                  "ApiGatewayResourceProxyVar": {
                    "Type": "AWS::ApiGateway::Resource",
                    "Properties": {
                      "ParentId": {
                        "Fn::GetAtt": [
                          "ApiGatewayRestApi",
                          "RootResourceId"
                        ]
                      },
                      "PathPart": "{proxy+}",
                      "RestApiId": {
                        "Ref": "ApiGatewayRestApi"
                      }
                    }
                  },
                  "ApiGatewayMethodAny": {
                    "Type": "AWS::ApiGateway::Method",
                    "Properties": {
                      "HttpMethod": "ANY",
                      "RequestParameters": {},
                      "ResourceId": {
                        "Fn::GetAtt": [
                          "ApiGatewayRestApi",
                          "RootResourceId"
                        ]
                      },
                      "RestApiId": {
                        "Ref": "ApiGatewayRestApi"
                      },
                      "ApiKeyRequired": "<REDACTED>",
                      "AuthorizationType": "NONE",
                      "Integration": {
                        "IntegrationHttpMethod": "POST",
                        "Type": "AWS_PROXY",
                        "Uri": {
                          "Fn::Join": [
                            "",
                            [
                              "arn:",
                              {
                                "Ref": "AWS::Partition"
                              },
                              ":apigateway:",
                              {
                                "Ref": "AWS::Region"
                              },
                              ":lambda:path/2015-03-31/functions/",
                              {
                                "Fn::GetAtt": [
                                  "MainLambdaFunction",
                                  "Arn"
                                ]
                              },
                              "/invocations"
                            ]
                          ]
                        }
                      },
                      "MethodResponses": []
                    },
                    "DependsOn": [
                      "MainLambdaPermissionApiGateway"
                    ]
                  },
                  "ApiGatewayMethodProxyVarAny": {
                    "Type": "AWS::ApiGateway::Method",
                    "Properties": {
                      "HttpMethod": "ANY",
                      "RequestParameters": {},
                      "ResourceId": {
                        "Ref": "ApiGatewayResourceProxyVar"
                      },
                      "RestApiId": {
                        "Ref": "ApiGatewayRestApi"
                      },
                      "ApiKeyRequired": "<REDACTED>",
                      "AuthorizationType": "NONE",
                      "Integration": {
                        "IntegrationHttpMethod": "POST",
                        "Type": "AWS_PROXY",
                        "Uri": {
                          "Fn::Join": [
                            "",
                            [
                              "arn:",
                              {
                                "Ref": "AWS::Partition"
                              },
                              ":apigateway:",
                              {
                                "Ref": "AWS::Region"
                              },
                              ":lambda:path/2015-03-31/functions/",
                              {
                                "Fn::GetAtt": [
                                  "MainLambdaFunction",
                                  "Arn"
                                ]
                              },
                              "/invocations"
                            ]
                          ]
                        }
                      },
                      "MethodResponses": []
                    },
                    "DependsOn": [
                      "MainLambdaPermissionApiGateway"
                    ]
                  },
                  "ApiGatewayDeployment1729389083254": {
                    "Type": "AWS::ApiGateway::Deployment",
                    "Properties": {
                      "RestApiId": {
                        "Ref": "ApiGatewayRestApi"
                      },
                      "StageName": "dev"
                    },
                    "DependsOn": [
                      "ApiGatewayMethodAny",
                      "ApiGatewayMethodProxyVarAny"
                    ]
                  },
                  "MainLambdaPermissionApiGateway": {
                    "Type": "AWS::Lambda::Permission",
                    "Properties": {
                      "FunctionName": {
                        "Fn::GetAtt": [
                          "MainLambdaFunction",
                          "Arn"
                        ]
                      },
                      "Action": "lambda:InvokeFunction",
                      "Principal": "apigateway.amazonaws.com",
                      "SourceArn": {
                        "Fn::Join": [
                          "",
                          [
                            "arn:",
                            {
                              "Ref": "AWS::Partition"
                            },
                            ":execute-api:",
                            {
                              "Ref": "AWS::Region"
                            },
                            ":",
                            {
                              "Ref": "AWS::AccountId"
                            },
                            ":",
                            {
                              "Ref": "ApiGatewayRestApi"
                            },
                            "/*/*"
                          ]
                        ]
                      }
                    }
                  }
                },
                "Outputs": {
                  "ServerlessDeploymentBucketName": {
                    "Value": "serverless-framework-deployments-us-east-1-4b88c842-fa16",
                    "Export": {
                      "Name": "sls-starwars-api-dev-ServerlessDeploymentBucketName"
                    }
                  },
                  "MainLambdaFunctionQualifiedArn": {
                    "Description": "Current Lambda function version",
                    "Value": {
                      "Ref": "MainLambdaVersion5NNZ5akh00CMyrCCTqWh3fsBIltcwBfyVgr2QKffk"
                    },
                    "Export": {
                      "Name": "sls-starwars-api-dev-MainLambdaFunctionQualifiedArn"
                    }
                  },
                  "ServiceEndpoint": {
                    "Description": "URL of the service endpoint",
                    "Value": {
                      "Fn::Join": [
                        "",
                        [
                          "https://",
                          {
                            "Ref": "ApiGatewayRestApi"
                          },
                          ".execute-api.",
                          {
                            "Ref": "AWS::Region"
                          },
                          ".",
                          {
                            "Ref": "AWS::URLSuffix"
                          },
                          "/dev"
                        ]
                      ]
                    },
                    "Export": {
                      "Name": "sls-starwars-api-dev-ServiceEndpoint"
                    }
                  }
                }
              }
            },
            "functions": {
              "main": {
                "handler": "dist/serverless.handler",
                "events": [
                  {
                    "http": {
                      "path": "",
                      "method": "any",
                      "integration": "AWS_PROXY"
                    }
                  },
                  {
                    "http": {
                      "path": "{proxy+}",
                      "method": "any",
                      "integration": "AWS_PROXY"
                    }
                  }
                ],
                "vpc": {
                  "subnetIds": [
                    "subnet-0bf79a58960460c7e",
                    "subnet-055feaddca913028c",
                    "subnet-0e17a2d20a160af93",
                    "subnet-0dddebcd6bb360117",
                    "subnet-0ffdbdde1b7f4cbec",
                    "subnet-0b9b7771bef7496d9"
                  ],
                  "securityGroupIds": [
                    "sg-0565b976b97262683"
                  ]
                },
                "name": "starwars-api-dev-main",
                "package": {},
                "memory": 1024,
                "timeout": 6,
                "runtime": "nodejs18.x",
                "versionLogicalId": "MainLambdaVersion5NNZ5akh00CMyrCCTqWh3fsBIltcwBfyVgr2QKffk"
              }
            },
            "package": {
              "include": [
                "!node_modules/.prisma/client/**",
                "node_modules/.prisma/client/**",
                "!node_modules/.prisma/client/libquery_engine-*",
                "node_modules/.prisma/client/libquery_engine-rhel-*",
                "!node_modules/prisma/libquery_engine-*",
                "!node_modules/@prisma/engines/**",
                "!node_modules/.cache/prisma/**"
              ],
              "artifactsS3KeyDirname": "serverless/starwars-api/dev/code-artifacts",
              "deploymentBucket": "serverless-framework-deployments-us-east-1-4b88c842-fa16",
              "artifact": ".serverless\\starwars-api.zip",
              "artifactDirectoryName": "serverless/starwars-api/dev/1729389127459-2024-10-20T01:52:07.459Z"
            }
          },
          "configFileDirPath": "D:\\otros\\Softekk_Prueba_Tecnica\\starwars-api",
          "config": {
            "type": "env"
          },
          "options": {},
          "stage": "dev",
          "dashboard": null,
          "logger": {
            "namespace": "s:core:resolver:env",
            "prefix": null,
            "prefixColor": null
          },
          "_credentialsPromise": "<REDACTED>"
        },
        "resolvers": {}
      }
    },
    "composeServiceName": null,
    "servicePath": "D:\\otros\\Softekk_Prueba_Tecnica\\starwars-api",
    "serviceConfigFileName": "serverless.yml",
    "service": {
      "service": "starwars-api",
      "plugins": [
        "serverless-jetpack",
        "serverless-offline"
      ],
      "useDotenv": true,
      "frameworkVersion": "4",
      "provider": {
        "name": "aws",
        "runtime": "nodejs18.x",
        "environment": {
          "SWAPI_URL": "https://swapi.py4e.com/api",
          "DATABASE_URL": "mysql://admin:zNvem55R6rGVHLZ@evaluacion-softtek.c9qmai44axdb.us-east-1.rds.amazonaws.com:3306/starwars?schema=public"
        },
        "vpc": {
          "subnetIds": [
            "subnet-0bf79a58960460c7e",
            "subnet-055feaddca913028c",
            "subnet-0e17a2d20a160af93",
            "subnet-0dddebcd6bb360117",
            "subnet-0ffdbdde1b7f4cbec",
            "subnet-0b9b7771bef7496d9"
          ],
          "securityGroupIds": [
            "sg-0565b976b97262683"
          ]
        },
        "apiGateway": {
          "name": "starwars-api-gateway",
          "version": "v2",
          "cors": {
            "origins": [
              "*"
            ],
            "methods": [
              "GET",
              "POST",
              "PUT",
              "DELETE",
              "HEAD"
            ],
            "headers": [
              "Content-Type",
              "Authorization"
            ],
            "allowCredentials": "<REDACTED>"
          }
        },
        "stage": "dev",
        "region": "us-east-1",
        "versionFunctions": true,
        "compiledCloudFormationTemplate": {
          "AWSTemplateFormatVersion": "2010-09-09",
          "Description": "The AWS CloudFormation template for this Serverless application",
          "Resources": {
            "MainLogGroup": {
              "Type": "AWS::Logs::LogGroup",
              "Properties": {
                "LogGroupName": "/aws/lambda/starwars-api-dev-main"
              }
            },
            "IamRoleLambdaExecution": {
              "Type": "AWS::IAM::Role",
              "Properties": {
                "AssumeRolePolicyDocument": {
                  "Version": "2012-10-17",
                  "Statement": [
                    {
                      "Effect": "Allow",
                      "Principal": {
                        "Service": [
                          "lambda.amazonaws.com"
                        ]
                      },
                      "Action": [
                        "sts:AssumeRole"
                      ]
                    }
                  ]
                },
                "Policies": [
                  {
                    "PolicyName": {
                      "Fn::Join": [
                        "-",
                        [
                          "starwars-api",
                          "dev",
                          "lambda"
                        ]
                      ]
                    },
                    "PolicyDocument": {
                      "Version": "2012-10-17",
                      "Statement": [
                        {
                          "Effect": "Allow",
                          "Action": [
                            "logs:CreateLogStream",
                            "logs:CreateLogGroup",
                            "logs:TagResource"
                          ],
                          "Resource": [
                            {
                              "Fn::Sub": "arn:${AWS::Partition}:logs:${AWS::Region}:${AWS::AccountId}:log-group:/aws/lambda/starwars-api-dev*:*"
                            }
                          ]
                        },
                        {
                          "Effect": "Allow",
                          "Action": [
                            "logs:PutLogEvents"
                          ],
                          "Resource": [
                            {
                              "Fn::Sub": "arn:${AWS::Partition}:logs:${AWS::Region}:${AWS::AccountId}:log-group:/aws/lambda/starwars-api-dev*:*:*"
                            }
                          ]
                        }
                      ]
                    }
                  }
                ],
                "Path": "/",
                "RoleName": {
                  "Fn::Join": [
                    "-",
                    [
                      "starwars-api",
                      "dev",
                      {
                        "Ref": "AWS::Region"
                      },
                      "lambdaRole"
                    ]
                  ]
                },
                "ManagedPolicyArns": [
                  {
                    "Fn::Join": [
                      "",
                      [
                        "arn:",
                        {
                          "Ref": "AWS::Partition"
                        },
                        ":iam::aws:policy/service-role/AWSLambdaVPCAccessExecutionRole"
                      ]
                    ]
                  }
                ]
              }
            },
            "MainLambdaFunction": {
              "Type": "AWS::Lambda::Function",
              "Properties": {
                "Code": {
                  "S3Bucket": "serverless-framework-deployments-us-east-1-4b88c842-fa16",
                  "S3Key": "serverless/starwars-api/dev/1729389127459-2024-10-20T01:52:07.459Z/starwars-api.zip"
                },
                "Handler": "dist/serverless.handler",
                "Runtime": "nodejs18.x",
                "FunctionName": "starwars-api-dev-main",
                "MemorySize": 1024,
                "Timeout": 6,
                "Environment": {
                  "Variables": {
                    "SWAPI_URL": "https://swapi.py4e.com/api",
                    "DATABASE_URL": "mysql://admin:zNvem55R6rGVHLZ@evaluacion-softtek.c9qmai44axdb.us-east-1.rds.amazonaws.com:3306/starwars?schema=public"
                  }
                },
                "Role": {
                  "Fn::GetAtt": [
                    "IamRoleLambdaExecution",
                    "Arn"
                  ]
                },
                "VpcConfig": {
                  "SecurityGroupIds": [
                    "sg-0565b976b97262683"
                  ],
                  "SubnetIds": [
                    "subnet-0bf79a58960460c7e",
                    "subnet-055feaddca913028c",
                    "subnet-0e17a2d20a160af93",
                    "subnet-0dddebcd6bb360117",
                    "subnet-0ffdbdde1b7f4cbec",
                    "subnet-0b9b7771bef7496d9"
                  ]
                }
              },
              "DependsOn": [
                "MainLogGroup"
              ]
            },
            "MainLambdaVersion5NNZ5akh00CMyrCCTqWh3fsBIltcwBfyVgr2QKffk": {
              "Type": "AWS::Lambda::Version",
              "DeletionPolicy": "Retain",
              "Properties": {
                "FunctionName": {
                  "Ref": "MainLambdaFunction"
                },
                "CodeSha256": "qRbSlCBV8HAakXSem4jfLrWCoaN1gpgOkE8DB3/Du44="
              }
            },
            "ApiGatewayRestApi": {
              "Type": "AWS::ApiGateway::RestApi",
              "Properties": {
                "Name": "dev-starwars-api",
                "EndpointConfiguration": {
                  "Types": [
                    "EDGE"
                  ]
                },
                "Policy": ""
              }
            },
            "ApiGatewayResourceProxyVar": {
              "Type": "AWS::ApiGateway::Resource",
              "Properties": {
                "ParentId": {
                  "Fn::GetAtt": [
                    "ApiGatewayRestApi",
                    "RootResourceId"
                  ]
                },
                "PathPart": "{proxy+}",
                "RestApiId": {
                  "Ref": "ApiGatewayRestApi"
                }
              }
            },
            "ApiGatewayMethodAny": {
              "Type": "AWS::ApiGateway::Method",
              "Properties": {
                "HttpMethod": "ANY",
                "RequestParameters": {},
                "ResourceId": {
                  "Fn::GetAtt": [
                    "ApiGatewayRestApi",
                    "RootResourceId"
                  ]
                },
                "RestApiId": {
                  "Ref": "ApiGatewayRestApi"
                },
                "ApiKeyRequired": "<REDACTED>",
                "AuthorizationType": "NONE",
                "Integration": {
                  "IntegrationHttpMethod": "POST",
                  "Type": "AWS_PROXY",
                  "Uri": {
                    "Fn::Join": [
                      "",
                      [
                        "arn:",
                        {
                          "Ref": "AWS::Partition"
                        },
                        ":apigateway:",
                        {
                          "Ref": "AWS::Region"
                        },
                        ":lambda:path/2015-03-31/functions/",
                        {
                          "Fn::GetAtt": [
                            "MainLambdaFunction",
                            "Arn"
                          ]
                        },
                        "/invocations"
                      ]
                    ]
                  }
                },
                "MethodResponses": []
              },
              "DependsOn": [
                "MainLambdaPermissionApiGateway"
              ]
            },
            "ApiGatewayMethodProxyVarAny": {
              "Type": "AWS::ApiGateway::Method",
              "Properties": {
                "HttpMethod": "ANY",
                "RequestParameters": {},
                "ResourceId": {
                  "Ref": "ApiGatewayResourceProxyVar"
                },
                "RestApiId": {
                  "Ref": "ApiGatewayRestApi"
                },
                "ApiKeyRequired": "<REDACTED>",
                "AuthorizationType": "NONE",
                "Integration": {
                  "IntegrationHttpMethod": "POST",
                  "Type": "AWS_PROXY",
                  "Uri": {
                    "Fn::Join": [
                      "",
                      [
                        "arn:",
                        {
                          "Ref": "AWS::Partition"
                        },
                        ":apigateway:",
                        {
                          "Ref": "AWS::Region"
                        },
                        ":lambda:path/2015-03-31/functions/",
                        {
                          "Fn::GetAtt": [
                            "MainLambdaFunction",
                            "Arn"
                          ]
                        },
                        "/invocations"
                      ]
                    ]
                  }
                },
                "MethodResponses": []
              },
              "DependsOn": [
                "MainLambdaPermissionApiGateway"
              ]
            },
            "ApiGatewayDeployment1729389083254": {
              "Type": "AWS::ApiGateway::Deployment",
              "Properties": {
                "RestApiId": {
                  "Ref": "ApiGatewayRestApi"
                },
                "StageName": "dev"
              },
              "DependsOn": [
                "ApiGatewayMethodAny",
                "ApiGatewayMethodProxyVarAny"
              ]
            },
            "MainLambdaPermissionApiGateway": {
              "Type": "AWS::Lambda::Permission",
              "Properties": {
                "FunctionName": {
                  "Fn::GetAtt": [
                    "MainLambdaFunction",
                    "Arn"
                  ]
                },
                "Action": "lambda:InvokeFunction",
                "Principal": "apigateway.amazonaws.com",
                "SourceArn": {
                  "Fn::Join": [
                    "",
                    [
                      "arn:",
                      {
                        "Ref": "AWS::Partition"
                      },
                      ":execute-api:",
                      {
                        "Ref": "AWS::Region"
                      },
                      ":",
                      {
                        "Ref": "AWS::AccountId"
                      },
                      ":",
                      {
                        "Ref": "ApiGatewayRestApi"
                      },
                      "/*/*"
                    ]
                  ]
                }
              }
            }
          },
          "Outputs": {
            "ServerlessDeploymentBucketName": {
              "Value": "serverless-framework-deployments-us-east-1-4b88c842-fa16",
              "Export": {
                "Name": "sls-starwars-api-dev-ServerlessDeploymentBucketName"
              }
            },
            "MainLambdaFunctionQualifiedArn": {
              "Description": "Current Lambda function version",
              "Value": {
                "Ref": "MainLambdaVersion5NNZ5akh00CMyrCCTqWh3fsBIltcwBfyVgr2QKffk"
              },
              "Export": {
                "Name": "sls-starwars-api-dev-MainLambdaFunctionQualifiedArn"
              }
            },
            "ServiceEndpoint": {
              "Description": "URL of the service endpoint",
              "Value": {
                "Fn::Join": [
                  "",
                  [
                    "https://",
                    {
                      "Ref": "ApiGatewayRestApi"
                    },
                    ".execute-api.",
                    {
                      "Ref": "AWS::Region"
                    },
                    ".",
                    {
                      "Ref": "AWS::URLSuffix"
                    },
                    "/dev"
                  ]
                ]
              },
              "Export": {
                "Name": "sls-starwars-api-dev-ServiceEndpoint"
              }
            }
          }
        }
      },
      "functions": {
        "main": {
          "handler": "dist/serverless.handler",
          "events": [
            {
              "http": {
                "path": "",
                "method": "any",
                "integration": "AWS_PROXY"
              }
            },
            {
              "http": {
                "path": "{proxy+}",
                "method": "any",
                "integration": "AWS_PROXY"
              }
            }
          ],
          "vpc": {
            "subnetIds": [
              "subnet-0bf79a58960460c7e",
              "subnet-055feaddca913028c",
              "subnet-0e17a2d20a160af93",
              "subnet-0dddebcd6bb360117",
              "subnet-0ffdbdde1b7f4cbec",
              "subnet-0b9b7771bef7496d9"
            ],
            "securityGroupIds": [
              "sg-0565b976b97262683"
            ]
          },
          "name": "starwars-api-dev-main",
          "package": {},
          "memory": 1024,
          "timeout": 6,
          "runtime": "nodejs18.x",
          "versionLogicalId": "MainLambdaVersion5NNZ5akh00CMyrCCTqWh3fsBIltcwBfyVgr2QKffk"
        }
      },
      "package": {
        "include": [
          "!node_modules/.prisma/client/**",
          "node_modules/.prisma/client/**",
          "!node_modules/.prisma/client/libquery_engine-*",
          "node_modules/.prisma/client/libquery_engine-rhel-*",
          "!node_modules/prisma/libquery_engine-*",
          "!node_modules/@prisma/engines/**",
          "!node_modules/.cache/prisma/**"
        ],
        "artifactsS3KeyDirname": "serverless/starwars-api/dev/code-artifacts",
        "deploymentBucket": "serverless-framework-deployments-us-east-1-4b88c842-fa16",
        "artifact": ".serverless\\starwars-api.zip",
        "artifactDirectoryName": "serverless/starwars-api/dev/1729389127459-2024-10-20T01:52:07.459Z"
      }
    },
    "serviceRawFile": "service: starwars-api\r\n\r\nplugins:\r\n  - serverless-jetpack\r\n  - serverless-offline\r\n\r\nuseDotenv: true\r\n\r\nframeworkVersion: '4'\r\n\r\nprovider:\r\n  name: aws\r\n  runtime: nodejs18.x\r\n  environment:\r\n    SWAPI_URL: ${env:SWAPI_URL}\r\n    DATABASE_URL: ${env:DATABASE_URL}\r\n  # stage: production\r\n  # region: us-east-1\r\n  # memorySize: 2048\r\n  vpc:\r\n    subnetIds:\r\n      - subnet-0bf79a58960460c7e\r\n      - subnet-055feaddca913028c\r\n      - subnet-0e17a2d20a160af93\r\n      - subnet-0dddebcd6bb360117\r\n      - subnet-0ffdbdde1b7f4cbec\r\n      - subnet-0b9b7771bef7496d9\r\n    securityGroupIds:\r\n      - sg-0565b976b97262683\r\n  apiGateway:\r\n    name: starwars-api-gateway \r\n    version: v2\r\n    cors:\r\n      origins:\r\n        - '*'\r\n      methods:\r\n        - GET\r\n        - POST\r\n        - PUT\r\n        - DELETE\r\n        - HEAD\r\n      headers:\r\n        - Content-Type\r\n        - Authorization\r\n      allowCredentials: false\r\n\r\nfunctions:\r\n  main:\r\n    handler: dist/serverless.handler\r\n    events:\r\n      - http:\r\n          path: /\r\n          method: ANY\r\n      - http:\r\n          path: '{proxy+}'\r\n          method: ANY\r\n    vpc:\r\n      subnetIds:\r\n        - subnet-0bf79a58960460c7e\r\n        - subnet-055feaddca913028c\r\n        - subnet-0e17a2d20a160af93\r\n        - subnet-0dddebcd6bb360117\r\n        - subnet-0ffdbdde1b7f4cbec\r\n        - subnet-0b9b7771bef7496d9\r\n      securityGroupIds:\r\n        - sg-0565b976b97262683\r\n\r\npackage:\r\n  include:\r\n    - '!node_modules/.prisma/client/**'\r\n    - 'node_modules/.prisma/client/**'\r\n    - '!node_modules/.prisma/client/libquery_engine-*'\r\n    - 'node_modules/.prisma/client/libquery_engine-rhel-*'\r\n    - '!node_modules/prisma/libquery_engine-*'\r\n    - '!node_modules/@prisma/engines/**'\r\n    - '!node_modules/.cache/prisma/**'  ",
    "command": [
      "deploy"
    ],
    "options": {},
    "error": null,
    "params": {},
    "machineId": "7fd0b47a260727900e9a5f59d157da13",
    "stage": "dev",
    "accessKeyV2": "<REDACTED>",
    "accessKeyV1": "<REDACTED>",
    "orgId": "5d8b660e-6199-42aa-aa70-f3781f2d4faa",
    "orgName": "lucianodev",
    "userId": "4VS37R7mtQtpc24Ldk",
    "dashboard": {
      "isEnabledForService": false,
      "requiredAuthentication": false,
      "orgFeaturesInUse": null,
      "orgObservabilityIntegrations": null,
      "serviceAppId": null,
      "serviceProvider": null,
      "instanceParameters": null
    },
    "userName": "lucianodev",
    "subscription": null,
    "userEmail": "lfcc_1369@hotmail.com",
    "serviceProviderAwsRegion": "us-east-1",
    "serviceProviderAwsCredentials": "<REDACTED>",
    "serviceProviderAwsAccountId": "019728833766",
    "projectType": "traditional",
    "versionSf": "4.4.6",
    "serviceProviderAwsCfStackName": "starwars-api-dev",
    "integrations": {},
    "serviceUniqueId": "arn:aws:cloudformation:us-east-1:019728833766:stack/starwars-api-dev/d21a9fa0-8e76-11ef-8c64-0affe2c1d5ef",
    "serviceProviderAwsCfStackId": "arn:aws:cloudformation:us-east-1:019728833766:stack/starwars-api-dev/d21a9fa0-8e76-11ef-8c64-0affe2c1d5ef",
    "serviceProviderAwsCfStackCreated": "2024-10-20T00:04:05.514Z",
    "serviceProviderAwsCfStackUpdated": "2024-10-20T01:52:18.403Z",
    "serviceProviderAwsCfStackStatus": "UPDATE_COMPLETE",
    "serviceProviderAwsCfStackOutputs": [
      {
        "OutputKey": "MainLambdaFunctionQualifiedArn",
        "OutputValue": "arn:aws:lambda:us-east-1:019728833766:function:starwars-api-dev-main:6",
        "Description": "Current Lambda function version",
        "ExportName": "sls-starwars-api-dev-MainLambdaFunctionQualifiedArn"
      },
      {
        "OutputKey": "ServiceEndpoint",
        "OutputValue": "https://3z1u02ymi8.execute-api.us-east-1.amazonaws.com/dev",
        "Description": "URL of the service endpoint",
        "ExportName": "sls-starwars-api-dev-ServiceEndpoint"
      },
      {
        "OutputKey": "ServerlessDeploymentBucketName",
        "OutputValue": "serverless-framework-deployments-us-east-1-4b88c842-fa16",
        "ExportName": "sls-starwars-api-dev-ServerlessDeploymentBucketName"
      }
    ]
  }
}